pystructura/__init__.py
pystructura/test.py
pyStructura-0.1.dist-info/METADATA
pyStructura-0.1.dist-info/WHEEL
pyStructura-0.1.dist-info/top_level.txt
pyStructura-0.1.dist-info/RECORD
