Metadata-Version: 2.1
Name: pyStructura
Version: 0.1
Summary: A library for advanced data structures in Python
Author: Sukriti Sharma
Author-email: 1106.sharma@gmail.com
Requires-Python: >=3.7.4
